cam/__init__.py
cam/cam.py
cam/version.py
cam/web/nuxt.config.js
cam/web/package-lock.json
cam/web/package.json
cam/web/pages/index.vue
cam/web/plugins/element-ui.js
cam/web/server-middleware/get_config.js
cam/web/server-middleware/redis.js
cam/web/server-middleware/redis_v1.js
cam/web/static/favicon.ico
cam_tool-1.3.8.dist-info/METADATA
cam_tool-1.3.8.dist-info/WHEEL
cam_tool-1.3.8.dist-info/entry_points.txt
cam_tool-1.3.8.dist-info/top_level.txt
cam_tool-1.3.8.dist-info/RECORD
