Metadata-Version: 2.1
Name: cam-tool
Version: 1.3.8
Summary: Cloud Assignment Manager Tool
Home-page: https://github.com/fuzihaofzh/cam-tool
Author: 
Author-email: 
License: UNKNOWN
Keywords: Cloud Assignment Manager
Platform: UNKNOWN
Classifier: Programming Language :: Python :: 3.7
Requires-Dist: fire
Requires-Dist: pyyaml
Requires-Dist: redis
Requires-Dist: tabulate
Requires-Dist: GPUtil
Requires-Dist: psutil
